setup.py
modellingService/Constants.py
modellingService/Estimators.py
modellingService/Train.py
modellingService/Utils.py
modellingService/__init__.py
modelling_service_caps_3.egg-info/PKG-INFO
modelling_service_caps_3.egg-info/SOURCES.txt
modelling_service_caps_3.egg-info/dependency_links.txt
modelling_service_caps_3.egg-info/requires.txt
modelling_service_caps_3.egg-info/top_level.txt